plone.supermodel-2.0.5-py3.13-nspkg.pth
plone/supermodel/__init__.py
plone/supermodel/configure.zcml
plone/supermodel/converters.py
plone/supermodel/debug.py
plone/supermodel/directives.py
plone/supermodel/directives.rst
plone/supermodel/exportimport.py
plone/supermodel/fields.py
plone/supermodel/fields.rst
plone/supermodel/generated.py
plone/supermodel/interfaces.py
plone/supermodel/model.py
plone/supermodel/parser.py
plone/supermodel/patches.py
plone/supermodel/schema.rst
plone/supermodel/schemaclass.rst
plone/supermodel/serializer.py
plone/supermodel/tests.py
plone/supermodel/utils.py
plone_supermodel-2.0.5.dist-info/METADATA
plone_supermodel-2.0.5.dist-info/WHEEL
plone_supermodel-2.0.5.dist-info/namespace_packages.txt
plone_supermodel-2.0.5.dist-info/top_level.txt
plone_supermodel-2.0.5.dist-info/RECORD
