Metadata-Version: 2.4
Name: plone.supermodel
Version: 2.0.5
Summary: Serialize Zope schema definitions to and from XML
Home-page: https://github.com/plone/plone.supermodel
Author: Martin Aspeli
Author-email: optilude@gmail.com
License: BSD
Keywords: Plone XML schema
Classifier: Development Status :: 5 - Production/Stable
Classifier: Framework :: Plone
Classifier: Framework :: Plone :: 6.0
Classifier: Framework :: Plone :: Core
Classifier: Programming Language :: Python
Classifier: Programming Language :: Python :: 3.8
Classifier: Programming Language :: Python :: 3.9
Classifier: Programming Language :: Python :: 3.10
Classifier: Programming Language :: Python :: 3.11
Classifier: Topic :: Software Development :: Libraries :: Python Modules
Classifier: License :: OSI Approved :: BSD License
Requires-Python: >=3.8
Requires-Dist: setuptools
Requires-Dist: lxml
Requires-Dist: zope.component
Requires-Dist: zope.i18nmessageid
Requires-Dist: zope.interface
Requires-Dist: zope.schema>=4.1.0
Requires-Dist: zope.deferredimport
Requires-Dist: zope.dottedname
Requires-Dist: z3c.zcmlhook
Provides-Extra: lxml
Provides-Extra: plone-rfc822
Requires-Dist: plone.rfc822; extra == "plone-rfc822"
Provides-Extra: test
Requires-Dist: plone.rfc822; extra == "test"
Requires-Dist: zope.configuration[test]; extra == "test"
Dynamic: author
Dynamic: author-email
Dynamic: classifier
Dynamic: description
Dynamic: description-content-type
Dynamic: home-page
Dynamic: keywords
Dynamic: license
Dynamic: provides-extra
Dynamic: requires-dist
Dynamic: requires-python
Dynamic: summary
